Workbook

Sheet Payroll Calculations 
A1: Name | B1: ID Number | C1: NEC Eligibility | D1: TIN | E1: Gross Pay | F1: Bonus | G1: Yearly Bonus | H1: WCIF | I1: Trade Union | J1: NEC | K1: NEC Employee | L1: NSSA | M1: NSSA Employee | N1: Taxable Income | O1: Tax Rate | P1: Deduction | Q1: PAYE | R1: AIDS Levy | S1: PAYE ZIMRA | T1: Total Deductions | U1: Net Pay | V1: Advance Deductions | W1: Net Pay after Deductions
A2: Wisdom Muzambi | C2: FALSE | D2: XXXXXX | E2: 1200 | H2: =Table1[[#This Row],[Gross Pay]]*'Tax Tables'!$B$16 -> 15 | I2: =Table1[[#This Row],[Gross Pay]]*'Tax Tables'!$B$15 -> 0 | J2: =IF(Table1[[#This Row],[NEC Eligibility]]=TRUE,Table1[[#This Row],[Gross Pay]]*'Tax Tables'!$B$14,"") | K2: =IFERROR(Table1[[#This Row],[NEC]]/2,"0") -> 0 | L2: =IF(Table1[[#This Row],[Gross Pay]]>'Tax Tables'!$D$13,'Tax Tables'!$D$13*'Tax Tables'!$B$13,Table1[[#This Row],[Gross Pay]]*'Tax Tables'!$B$13) -> 63 | M2: =Table1[[#This Row],[NSSA]]/2 -> 31.5 | N2: =Table1[[#This Row],[Gross Pay]]-Table1[[#This Row],[Trade Union]]-Table1[[#This Row],[NEC Employee]]-Table1[[#This Row],[NSSA Employee]] -> 1168.5 | O2: =IF(Table1[[#This Row],[Taxable Income]]<='Tax Tables'!$B$3,'Tax Tables'!$C$3,IF(Table1[[#This Row],[Taxable Income]]<='Tax Tables'!$B$4,'Tax Tables'!$C$4,IF(Table1[[#This Row],[Taxable Income]]<='Tax Tables'!$B$5,'Tax Tables'!$C$5,IF(Table1[[#This Row],[Taxable Income]]<='Tax Tables'!$B$6,'Tax Tables'!$C$6,IF(Table1[[#This Row],[Taxable Income]]<='Tax Tables'!$B$7,'Tax Tables'!$C$7,IF(Table1[[#This Row],[Taxable Income]]>='Tax Tables'!$A$8,'Tax Tables'!$C$8)))))) -> 0.3 | P2: =IF(Table1[[#This Row],[Tax Rate]]='Tax Tables'!$C$3,'Tax Tables'!$D$3,IF(Table1[[#This Row],[Tax Rate]]='Tax Tables'!$C$4,'Tax Tables'!$D$4,IF(Table1[[#This Row],[Tax Rate]]='Tax Tables'!$C$5,'Tax Tables'!$D$5,IF(Table1[[#This Row],[Tax Rate]]='Tax Tables'!$C$6,'Tax Tables'!$D$6,IF(Table1[[#This Row],[Tax Rate]]='Tax Tables'!$C$7,'Tax Tables'!$D$7,IF(Table1[[#This Row],[Tax Rate]]='Tax Tables'!$C$8,'Tax Tables'!$D$8)))))) -> 85 | Q2: =Table1[[#This Row],[Taxable Income]]*Table1[[#This Row],[Tax Rate]]-(Table1[[#This Row],[Deduction]]) -> 265.55 | R2: =Table1[[#This Row],[PAYE]]*'Tax Tables'!$B$11 -> 7.9665 | S2: =Table1[[#This Row],[PAYE]]+Table1[[#This Row],[AIDS Levy]] -> 273.5165 | T2: =Table1[[#This Row],[PAYE]]+Table1[[#This Row],[AIDS Levy]]+Table1[[#This Row],[NSSA Employee]]+Table1[[#This Row],[NEC Employee]] -> 305.0165 | U2: =Table1[[#This Row],[Taxable Income]]-Table1[[#This Row],[PAYE ZIMRA]]+Table1[[#This Row],[Yearly Bonus]]+Table1[[#This Row],[Bonus]] -> 894.9835 | V2: 0 | W2: =Table1[[#This Row],[Net Pay]]-Table1[[#This Row],[Advance Deductions]] -> 894.9835
C3: TRUE | H3: =Table1[[#This Row],[Gross Pay]]*'Tax Tables'!$B$16 -> 0 | I3: =Table1[[#This Row],[Gross Pay]]*'Tax Tables'!$B$15 -> 0 | J3: =IF(Table1[[#This Row],[NEC Eligibility]]=TRUE,Table1[[#This Row],[Gross Pay]]*'Tax Tables'!$B$14,"") -> 0 | K3: =IFERROR(Table1[[#This Row],[NEC]]/2,"0") -> 0 | L3: =IF(Table1[[#This Row],[Gross Pay]]>'Tax Tables'!$D$13,'Tax Tables'!$D$13*'Tax Tables'!$B$13,Table1[[#This Row],[Gross Pay]]*'Tax Tables'!$B$13) -> 0 | M3: =Table1[[#This Row],[NSSA]]/2 -> 0 | N3: =Table1[[#This Row],[Gross Pay]]-Table1[[#This Row],[Trade Union]]-Table1[[#This Row],[NEC Employee]]-Table1[[#This Row],[NSSA Employee]] -> 0 | O3: =IF(Table1[[#This Row],[Taxable Income]]<='Tax Tables'!$B$3,'Tax Tables'!$C$3,IF(Table1[[#This Row],[Taxable Income]]<='Tax Tables'!$B$4,'Tax Tables'!$C$4,IF(Table1[[#This Row],[Taxable Income]]<='Tax Tables'!$B$5,'Tax Tables'!$C$5,IF(Table1[[#This Row],[Taxable Income]]<='Tax Tables'!$B$6,'Tax Tables'!$C$6,IF(Table1[[#This Row],[Taxable Income]]<='Tax Tables'!$B$7,'Tax Tables'!$C$7,IF(Table1[[#This Row],[Taxable Income]]>='Tax Tables'!$A$8,'Tax Tables'!$C$8)))))) -> 0 | P3: =IF(Table1[[#This Row],[Tax Rate]]='Tax Tables'!$C$3,'Tax Tables'!$D$3,IF(Table1[[#This Row],[Tax Rate]]='Tax Tables'!$C$4,'Tax Tables'!$D$4,IF(Table1[[#This Row],[Tax Rate]]='Tax Tables'!$C$5,'Tax Tables'!$D$5,IF(Table1[[#This Row],[Tax Rate]]='Tax Tables'!$C$6,'Tax Tables'!$D$6,IF(Table1[[#This Row],[Tax Rate]]='Tax Tables'!$C$7,'Tax Tables'!$D$7,IF(Table1[[#This Row],[Tax Rate]]='Tax Tables'!$C$8,'Tax Tables'!$D$8)))))) -> 0 | Q3: =Table1[[#This Row],[Taxable Income]]*Table1[[#This Row],[Tax Rate]]-(Table1[[#This Row],[Deduction]]) -> 0 | R3: =Table1[[#This Row],[PAYE]]*'Tax Tables'!$B$11 -> 0 | S3: =Table1[[#This Row],[PAYE]]+Table1[[#This Row],[AIDS Levy]] -> 0 | T3: =Table1[[#This Row],[PAYE]]+Table1[[#This Row],[AIDS Levy]]+Table1[[#This Row],[NSSA Employee]]+Table1[[#This Row],[NEC Employee]] -> 0 | U3: =Table1[[#This Row],[Taxable Income]]-Table1[[#This Row],[PAYE ZIMRA]]+Table1[[#This Row],[Yearly Bonus]]+Table1[[#This Row],[Bonus]] -> 0 | W3: =Table1[[#This Row],[Net Pay]]-Table1[[#This Row],[Advance Deductions]] -> 0
C4: TRUE | H4: =Table1[[#This Row],[Gross Pay]]*'Tax Tables'!$B$16 -> 0 | I4: =Table1[[#This Row],[Gross Pay]]*'Tax Tables'!$B$15 -> 0 | J4: =IF(Table1[[#This Row],[NEC Eligibility]]=TRUE,Table1[[#This Row],[Gross Pay]]*'Tax Tables'!$B$14,"") -> 0 | K4: =IFERROR(Table1[[#This Row],[NEC]]/2,"0") -> 0 | L4: =IF(Table1[[#This Row],[Gross Pay]]>'Tax Tables'!$D$13,'Tax Tables'!$D$13*'Tax Tables'!$B$13,Table1[[#This Row],[Gross Pay]]*'Tax Tables'!$B$13) -> 0 | M4: =Table1[[#This Row],[NSSA]]/2 -> 0 | N4: =Table1[[#This Row],[Gross Pay]]-Table1[[#This Row],[Trade Union]]-Table1[[#This Row],[NEC Employee]]-Table1[[#This Row],[NSSA Employee]] -> 0 | O4: =IF(Table1[[#This Row],[Taxable Income]]<='Tax Tables'!$B$3,'Tax Tables'!$C$3,IF(Table1[[#This Row],[Taxable Income]]<='Tax Tables'!$B$4,'Tax Tables'!$C$4,IF(Table1[[#This Row],[Taxable Income]]<='Tax Tables'!$B$5,'Tax Tables'!$C$5,IF(Table1[[#This Row],[Taxable Income]]<='Tax Tables'!$B$6,'Tax Tables'!$C$6,IF(Table1[[#This Row],[Taxable Income]]<='Tax Tables'!$B$7,'Tax Tables'!$C$7,IF(Table1[[#This Row],[Taxable Income]]>='Tax Tables'!$A$8,'Tax Tables'!$C$8)))))) -> 0 | P4: =IF(Table1[[#This Row],[Tax Rate]]='Tax Tables'!$C$3,'Tax Tables'!$D$3,IF(Table1[[#This Row],[Tax Rate]]='Tax Tables'!$C$4,'Tax Tables'!$D$4,IF(Table1[[#This Row],[Tax Rate]]='Tax Tables'!$C$5,'Tax Tables'!$D$5,IF(Table1[[#This Row],[Tax Rate]]='Tax Tables'!$C$6,'Tax Tables'!$D$6,IF(Table1[[#This Row],[Tax Rate]]='Tax Tables'!$C$7,'Tax Tables'!$D$7,IF(Table1[[#This Row],[Tax Rate]]='Tax Tables'!$C$8,'Tax Tables'!$D$8)))))) -> 0 | Q4: =Table1[[#This Row],[Taxable Income]]*Table1[[#This Row],[Tax Rate]]-(Table1[[#This Row],[Deduction]]) -> 0 | R4: =Table1[[#This Row],[PAYE]]*'Tax Tables'!$B$11 -> 0 | S4: =Table1[[#This Row],[PAYE]]+Table1[[#This Row],[AIDS Levy]] -> 0 | T4: =Table1[[#This Row],[PAYE]]+Table1[[#This Row],[AIDS Levy]]+Table1[[#This Row],[NSSA Employee]]+Table1[[#This Row],[NEC Employee]] -> 0 | U4: =Table1[[#This Row],[Taxable Income]]-Table1[[#This Row],[PAYE ZIMRA]]+Table1[[#This Row],[Yearly Bonus]]+Table1[[#This Row],[Bonus]] -> 0 | V4: 0 | W4: =Table1[[#This Row],[Net Pay]]-Table1[[#This Row],[Advance Deductions]] -> 0
C5: FALSE | H5: =Table1[[#This Row],[Gross Pay]]*'Tax Tables'!$B$16 -> 0 | I5: =Table1[[#This Row],[Gross Pay]]*'Tax Tables'!$B$15 -> 0 | J5: =IF(Table1[[#This Row],[NEC Eligibility]]=TRUE,Table1[[#This Row],[Gross Pay]]*'Tax Tables'!$B$14,"") | K5: =IFERROR(Table1[[#This Row],[NEC]]/2,"0") -> 0 | L5: =IF(Table1[[#This Row],[Gross Pay]]>'Tax Tables'!$D$13,'Tax Tables'!$D$13*'Tax Tables'!$B$13,Table1[[#This Row],[Gross Pay]]*'Tax Tables'!$B$13) -> 0 | M5: =Table1[[#This Row],[NSSA]]/2 -> 0 | N5: =Table1[[#This Row],[Gross Pay]]-Table1[[#This Row],[Trade Union]]-Table1[[#This Row],[NEC Employee]]-Table1[[#This Row],[NSSA Employee]] -> 0 | O5: =IF(Table1[[#This Row],[Taxable Income]]<='Tax Tables'!$B$3,'Tax Tables'!$C$3,IF(Table1[[#This Row],[Taxable Income]]<='Tax Tables'!$B$4,'Tax Tables'!$C$4,IF(Table1[[#This Row],[Taxable Income]]<='Tax Tables'!$B$5,'Tax Tables'!$C$5,IF(Table1[[#This Row],[Taxable Income]]<='Tax Tables'!$B$6,'Tax Tables'!$C$6,IF(Table1[[#This Row],[Taxable Income]]<='Tax Tables'!$B$7,'Tax Tables'!$C$7,IF(Table1[[#This Row],[Taxable Income]]>='Tax Tables'!$A$8,'Tax Tables'!$C$8)))))) -> 0 | P5: =IF(Table1[[#This Row],[Tax Rate]]='Tax Tables'!$C$3,'Tax Tables'!$D$3,IF(Table1[[#This Row],[Tax Rate]]='Tax Tables'!$C$4,'Tax Tables'!$D$4,IF(Table1[[#This Row],[Tax Rate]]='Tax Tables'!$C$5,'Tax Tables'!$D$5,IF(Table1[[#This Row],[Tax Rate]]='Tax Tables'!$C$6,'Tax Tables'!$D$6,IF(Table1[[#This Row],[Tax Rate]]='Tax Tables'!$C$7,'Tax Tables'!$D$7,IF(Table1[[#This Row],[Tax Rate]]='Tax Tables'!$C$8,'Tax Tables'!$D$8)))))) -> 0 | Q5: =Table1[[#This Row],[Taxable Income]]*Table1[[#This Row],[Tax Rate]]-(Table1[[#This Row],[Deduction]]) -> 0 | R5: =Table1[[#This Row],[PAYE]]*'Tax Tables'!$B$11 -> 0 | S5: =Table1[[#This Row],[PAYE]]+Table1[[#This Row],[AIDS Levy]] -> 0 | T5: =Table1[[#This Row],[PAYE]]+Table1[[#This Row],[AIDS Levy]]+Table1[[#This Row],[NSSA Employee]]+Table1[[#This Row],[NEC Employee]] -> 0 | U5: =Table1[[#This Row],[Taxable Income]]-Table1[[#This Row],[PAYE ZIMRA]]+Table1[[#This Row],[Yearly Bonus]]+Table1[[#This Row],[Bonus]] -> 0 | V5: 0 | W5: =Table1[[#This Row],[Net Pay]]-Table1[[#This Row],[Advance Deductions]] -> 0
C6: TRUE | H6: =Table1[[#This Row],[Gross Pay]]*'Tax Tables'!$B$16 -> 0 | I6: =Table1[[#This Row],[Gross Pay]]*'Tax Tables'!$B$15 -> 0 | J6: =IF(Table1[[#This Row],[NEC Eligibility]]=TRUE,Table1[[#This Row],[Gross Pay]]*'Tax Tables'!$B$14,"") -> 0 | K6: =IFERROR(Table1[[#This Row],[NEC]]/2,"0") -> 0 | L6: =IF(Table1[[#This Row],[Gross Pay]]>'Tax Tables'!$D$13,'Tax Tables'!$D$13*'Tax Tables'!$B$13,Table1[[#This Row],[Gross Pay]]*'Tax Tables'!$B$13) -> 0 | M6: =Table1[[#This Row],[NSSA]]/2 -> 0 | N6: =Table1[[#This Row],[Gross Pay]]-Table1[[#This Row],[Trade Union]]-Table1[[#This Row],[NEC Employee]]-Table1[[#This Row],[NSSA Employee]] -> 0 | O6: =IF(Table1[[#This Row],[Taxable Income]]<='Tax Tables'!$B$3,'Tax Tables'!$C$3,IF(Table1[[#This Row],[Taxable Income]]<='Tax Tables'!$B$4,'Tax Tables'!$C$4,IF(Table1[[#This Row],[Taxable Income]]<='Tax Tables'!$B$5,'Tax Tables'!$C$5,IF(Table1[[#This Row],[Taxable Income]]<='Tax Tables'!$B$6,'Tax Tables'!$C$6,IF(Table1[[#This Row],[Taxable Income]]<='Tax Tables'!$B$7,'Tax Tables'!$C$7,IF(Table1[[#This Row],[Taxable Income]]>='Tax Tables'!$A$8,'Tax Tables'!$C$8)))))) -> 0 | P6: =IF(Table1[[#This Row],[Tax Rate]]='Tax Tables'!$C$3,'Tax Tables'!$D$3,IF(Table1[[#This Row],[Tax Rate]]='Tax Tables'!$C$4,'Tax Tables'!$D$4,IF(Table1[[#This Row],[Tax Rate]]='Tax Tables'!$C$5,'Tax Tables'!$D$5,IF(Table1[[#This Row],[Tax Rate]]='Tax Tables'!$C$6,'Tax Tables'!$D$6,IF(Table1[[#This Row],[Tax Rate]]='Tax Tables'!$C$7,'Tax Tables'!$D$7,IF(Table1[[#This Row],[Tax Rate]]='Tax Tables'!$C$8,'Tax Tables'!$D$8)))))) -> 0 | Q6: =Table1[[#This Row],[Taxable Income]]*Table1[[#This Row],[Tax Rate]]-(Table1[[#This Row],[Deduction]]) -> 0 | R6: =Table1[[#This Row],[PAYE]]*'Tax Tables'!$B$11 -> 0 | S6: =Table1[[#This Row],[PAYE]]+Table1[[#This Row],[AIDS Levy]] -> 0 | T6: =Table1[[#This Row],[PAYE]]+Table1[[#This Row],[AIDS Levy]]+Table1[[#This Row],[NSSA Employee]]+Table1[[#This Row],[NEC Employee]] -> 0 | U6: =Table1[[#This Row],[Taxable Income]]-Table1[[#This Row],[PAYE ZIMRA]]+Table1[[#This Row],[Yearly Bonus]]+Table1[[#This Row],[Bonus]] -> 0 | V6: 0 | W6: =Table1[[#This Row],[Net Pay]]-Table1[[#This Row],[Advance Deductions]] -> 0
C7: TRUE | H7: =Table1[[#This Row],[Gross Pay]]*'Tax Tables'!$B$16 -> 0 | I7: =Table1[[#This Row],[Gross Pay]]*'Tax Tables'!$B$15 -> 0 | J7: =IF(Table1[[#This Row],[NEC Eligibility]]=TRUE,Table1[[#This Row],[Gross Pay]]*'Tax Tables'!$B$14,"") -> 0 | K7: =IFERROR(Table1[[#This Row],[NEC]]/2,"0") -> 0 | L7: =IF(Table1[[#This Row],[Gross Pay]]>'Tax Tables'!$D$13,'Tax Tables'!$D$13*'Tax Tables'!$B$13,Table1[[#This Row],[Gross Pay]]*'Tax Tables'!$B$13) -> 0 | M7: =Table1[[#This Row],[NSSA]]/2 -> 0 | N7: =Table1[[#This Row],[Gross Pay]]-Table1[[#This Row],[Trade Union]]-Table1[[#This Row],[NEC Employee]]-Table1[[#This Row],[NSSA Employee]] -> 0 | O7: =IF(Table1[[#This Row],[Taxable Income]]<='Tax Tables'!$B$3,'Tax Tables'!$C$3,IF(Table1[[#This Row],[Taxable Income]]<='Tax Tables'!$B$4,'Tax Tables'!$C$4,IF(Table1[[#This Row],[Taxable Income]]<='Tax Tables'!$B$5,'Tax Tables'!$C$5,IF(Table1[[#This Row],[Taxable Income]]<='Tax Tables'!$B$6,'Tax Tables'!$C$6,IF(Table1[[#This Row],[Taxable Income]]<='Tax Tables'!$B$7,'Tax Tables'!$C$7,IF(Table1[[#This Row],[Taxable Income]]>='Tax Tables'!$A$8,'Tax Tables'!$C$8)))))) -> 0 | P7: =IF(Table1[[#This Row],[Tax Rate]]='Tax Tables'!$C$3,'Tax Tables'!$D$3,IF(Table1[[#This Row],[Tax Rate]]='Tax Tables'!$C$4,'Tax Tables'!$D$4,IF(Table1[[#This Row],[Tax Rate]]='Tax Tables'!$C$5,'Tax Tables'!$D$5,IF(Table1[[#This Row],[Tax Rate]]='Tax Tables'!$C$6,'Tax Tables'!$D$6,IF(Table1[[#This Row],[Tax Rate]]='Tax Tables'!$C$7,'Tax Tables'!$D$7,IF(Table1[[#This Row],[Tax Rate]]='Tax Tables'!$C$8,'Tax Tables'!$D$8)))))) -> 0 | Q7: =Table1[[#This Row],[Taxable Income]]*Table1[[#This Row],[Tax Rate]]-(Table1[[#This Row],[Deduction]]) -> 0 | R7: =Table1[[#This Row],[PAYE]]*'Tax Tables'!$B$11 -> 0 | S7: =Table1[[#This Row],[PAYE]]+Table1[[#This Row],[AIDS Levy]] -> 0 | T7: =Table1[[#This Row],[PAYE]]+Table1[[#This Row],[AIDS Levy]]+Table1[[#This Row],[NSSA Employee]]+Table1[[#This Row],[NEC Employee]] -> 0 | U7: =Table1[[#This Row],[Taxable Income]]-Table1[[#This Row],[PAYE ZIMRA]]+Table1[[#This Row],[Yearly Bonus]]+Table1[[#This Row],[Bonus]] -> 0 | V7: 0 | W7: =Table1[[#This Row],[Net Pay]]-Table1[[#This Row],[Advance Deductions]] -> 0
C8: TRUE | H8: =Table1[[#This Row],[Gross Pay]]*'Tax Tables'!$B$16 -> 0 | I8: =Table1[[#This Row],[Gross Pay]]*'Tax Tables'!$B$15 -> 0 | J8: =IF(Table1[[#This Row],[NEC Eligibility]]=TRUE,Table1[[#This Row],[Gross Pay]]*'Tax Tables'!$B$14,"") -> 0 | K8: =IFERROR(Table1[[#This Row],[NEC]]/2,"0") -> 0 | L8: =IF(Table1[[#This Row],[Gross Pay]]>'Tax Tables'!$D$13,'Tax Tables'!$D$13*'Tax Tables'!$B$13,Table1[[#This Row],[Gross Pay]]*'Tax Tables'!$B$13) -> 0 | M8: =Table1[[#This Row],[NSSA]]/2 -> 0 | N8: =Table1[[#This Row],[Gross Pay]]-Table1[[#This Row],[Trade Union]]-Table1[[#This Row],[NEC Employee]]-Table1[[#This Row],[NSSA Employee]] -> 0 | O8: =IF(Table1[[#This Row],[Taxable Income]]<='Tax Tables'!$B$3,'Tax Tables'!$C$3,IF(Table1[[#This Row],[Taxable Income]]<='Tax Tables'!$B$4,'Tax Tables'!$C$4,IF(Table1[[#This Row],[Taxable Income]]<='Tax Tables'!$B$5,'Tax Tables'!$C$5,IF(Table1[[#This Row],[Taxable Income]]<='Tax Tables'!$B$6,'Tax Tables'!$C$6,IF(Table1[[#This Row],[Taxable Income]]<='Tax Tables'!$B$7,'Tax Tables'!$C$7,IF(Table1[[#This Row],[Taxable Income]]>='Tax Tables'!$A$8,'Tax Tables'!$C$8)))))) -> 0 | P8: =IF(Table1[[#This Row],[Tax Rate]]='Tax Tables'!$C$3,'Tax Tables'!$D$3,IF(Table1[[#This Row],[Tax Rate]]='Tax Tables'!$C$4,'Tax Tables'!$D$4,IF(Table1[[#This Row],[Tax Rate]]='Tax Tables'!$C$5,'Tax Tables'!$D$5,IF(Table1[[#This Row],[Tax Rate]]='Tax Tables'!$C$6,'Tax Tables'!$D$6,IF(Table1[[#This Row],[Tax Rate]]='Tax Tables'!$C$7,'Tax Tables'!$D$7,IF(Table1[[#This Row],[Tax Rate]]='Tax Tables'!$C$8,'Tax Tables'!$D$8)))))) -> 0 | Q8: =Table1[[#This Row],[Taxable Income]]*Table1[[#This Row],[Tax Rate]]-(Table1[[#This Row],[Deduction]]) -> 0 | R8: =Table1[[#This Row],[PAYE]]*'Tax Tables'!$B$11 -> 0 | S8: =Table1[[#This Row],[PAYE]]+Table1[[#This Row],[AIDS Levy]] -> 0 | T8: =Table1[[#This Row],[PAYE]]+Table1[[#This Row],[AIDS Levy]]+Table1[[#This Row],[NSSA Employee]]+Table1[[#This Row],[NEC Employee]] -> 0 | U8: =Table1[[#This Row],[Taxable Income]]-Table1[[#This Row],[PAYE ZIMRA]]+Table1[[#This Row],[Yearly Bonus]]+Table1[[#This Row],[Bonus]] -> 0 | V8: 0 | W8: =Table1[[#This Row],[Net Pay]]-Table1[[#This Row],[Advance Deductions]] -> 0
C9: TRUE | H9: =Table1[[#This Row],[Gross Pay]]*'Tax Tables'!$B$16 -> 0 | I9: =Table1[[#This Row],[Gross Pay]]*'Tax Tables'!$B$15 -> 0 | J9: =IF(Table1[[#This Row],[NEC Eligibility]]=TRUE,Table1[[#This Row],[Gross Pay]]*'Tax Tables'!$B$14,"") -> 0 | K9: =IFERROR(Table1[[#This Row],[NEC]]/2,"0") -> 0 | L9: =IF(Table1[[#This Row],[Gross Pay]]>'Tax Tables'!$D$13,'Tax Tables'!$D$13*'Tax Tables'!$B$13,Table1[[#This Row],[Gross Pay]]*'Tax Tables'!$B$13) -> 0 | M9: =Table1[[#This Row],[NSSA]]/2 -> 0 | N9: =Table1[[#This Row],[Gross Pay]]-Table1[[#This Row],[Trade Union]]-Table1[[#This Row],[NEC Employee]]-Table1[[#This Row],[NSSA Employee]] -> 0 | O9: =IF(Table1[[#This Row],[Taxable Income]]<='Tax Tables'!$B$3,'Tax Tables'!$C$3,IF(Table1[[#This Row],[Taxable Income]]<='Tax Tables'!$B$4,'Tax Tables'!$C$4,IF(Table1[[#This Row],[Taxable Income]]<='Tax Tables'!$B$5,'Tax Tables'!$C$5,IF(Table1[[#This Row],[Taxable Income]]<='Tax Tables'!$B$6,'Tax Tables'!$C$6,IF(Table1[[#This Row],[Taxable Income]]<='Tax Tables'!$B$7,'Tax Tables'!$C$7,IF(Table1[[#This Row],[Taxable Income]]>='Tax Tables'!$A$8,'Tax Tables'!$C$8)))))) -> 0 | P9: =IF(Table1[[#This Row],[Tax Rate]]='Tax Tables'!$C$3,'Tax Tables'!$D$3,IF(Table1[[#This Row],[Tax Rate]]='Tax Tables'!$C$4,'Tax Tables'!$D$4,IF(Table1[[#This Row],[Tax Rate]]='Tax Tables'!$C$5,'Tax Tables'!$D$5,IF(Table1[[#This Row],[Tax Rate]]='Tax Tables'!$C$6,'Tax Tables'!$D$6,IF(Table1[[#This Row],[Tax Rate]]='Tax Tables'!$C$7,'Tax Tables'!$D$7,IF(Table1[[#This Row],[Tax Rate]]='Tax Tables'!$C$8,'Tax Tables'!$D$8)))))) -> 0 | Q9: =Table1[[#This Row],[Taxable Income]]*Table1[[#This Row],[Tax Rate]]-(Table1[[#This Row],[Deduction]]) -> 0 | R9: =Table1[[#This Row],[PAYE]]*'Tax Tables'!$B$11 -> 0 | S9: =Table1[[#This Row],[PAYE]]+Table1[[#This Row],[AIDS Levy]] -> 0 | T9: =Table1[[#This Row],[PAYE]]+Table1[[#This Row],[AIDS Levy]]+Table1[[#This Row],[NSSA Employee]]+Table1[[#This Row],[NEC Employee]] -> 0 | U9: =Table1[[#This Row],[Taxable Income]]-Table1[[#This Row],[PAYE ZIMRA]]+Table1[[#This Row],[Yearly Bonus]]+Table1[[#This Row],[Bonus]] -> 0 | V9: 0 | W9: =Table1[[#This Row],[Net Pay]]-Table1[[#This Row],[Advance Deductions]] -> 0
C10: TRUE | H10: =Table1[[#This Row],[Gross Pay]]*'Tax Tables'!$B$16 -> 0 | I10: =Table1[[#This Row],[Gross Pay]]*'Tax Tables'!$B$15 -> 0 | J10: =IF(Table1[[#This Row],[NEC Eligibility]]=TRUE,Table1[[#This Row],[Gross Pay]]*'Tax Tables'!$B$14,"") -> 0 | K10: =IFERROR(Table1[[#This Row],[NEC]]/2,"0") -> 0 | L10: =IF(Table1[[#This Row],[Gross Pay]]>'Tax Tables'!$D$13,'Tax Tables'!$D$13*'Tax Tables'!$B$13,Table1[[#This Row],[Gross Pay]]*'Tax Tables'!$B$13) -> 0 | M10: =Table1[[#This Row],[NSSA]]/2 -> 0 | N10: =Table1[[#This Row],[Gross Pay]]-Table1[[#This Row],[Trade Union]]-Table1[[#This Row],[NEC Employee]]-Table1[[#This Row],[NSSA Employee]] -> 0 | O10: =IF(Table1[[#This Row],[Taxable Income]]<='Tax Tables'!$B$3,'Tax Tables'!$C$3,IF(Table1[[#This Row],[Taxable Income]]<='Tax Tables'!$B$4,'Tax Tables'!$C$4,IF(Table1[[#This Row],[Taxable Income]]<='Tax Tables'!$B$5,'Tax Tables'!$C$5,IF(Table1[[#This Row],[Taxable Income]]<='Tax Tables'!$B$6,'Tax Tables'!$C$6,IF(Table1[[#This Row],[Taxable Income]]<='Tax Tables'!$B$7,'Tax Tables'!$C$7,IF(Table1[[#This Row],[Taxable Income]]>='Tax Tables'!$A$8,'Tax Tables'!$C$8)))))) -> 0 | P10: =IF(Table1[[#This Row],[Tax Rate]]='Tax Tables'!$C$3,'Tax Tables'!$D$3,IF(Table1[[#This Row],[Tax Rate]]='Tax Tables'!$C$4,'Tax Tables'!$D$4,IF(Table1[[#This Row],[Tax Rate]]='Tax Tables'!$C$5,'Tax Tables'!$D$5,IF(Table1[[#This Row],[Tax Rate]]='Tax Tables'!$C$6,'Tax Tables'!$D$6,IF(Table1[[#This Row],[Tax Rate]]='Tax Tables'!$C$7,'Tax Tables'!$D$7,IF(Table1[[#This Row],[Tax Rate]]='Tax Tables'!$C$8,'Tax Tables'!$D$8)))))) -> 0 | Q10: =Table1[[#This Row],[Taxable Income]]*Table1[[#This Row],[Tax Rate]]-(Table1[[#This Row],[Deduction]]) -> 0 | R10: =Table1[[#This Row],[PAYE]]*'Tax Tables'!$B$11 -> 0 | S10: =Table1[[#This Row],[PAYE]]+Table1[[#This Row],[AIDS Levy]] -> 0 | T10: =Table1[[#This Row],[PAYE]]+Table1[[#This Row],[AIDS Levy]]+Table1[[#This Row],[NSSA Employee]]+Table1[[#This Row],[NEC Employee]] -> 0 | U10: =Table1[[#This Row],[Taxable Income]]-Table1[[#This Row],[PAYE ZIMRA]]+Table1[[#This Row],[Yearly Bonus]]+Table1[[#This Row],[Bonus]] -> 0 | V10: 0 | W10: =Table1[[#This Row],[Net Pay]]-Table1[[#This Row],[Advance Deductions]] -> 0
C11: TRUE | H11: =Table1[[#This Row],[Gross Pay]]*'Tax Tables'!$B$16 -> 0 | I11: =Table1[[#This Row],[Gross Pay]]*'Tax Tables'!$B$15 -> 0 | J11: =IF(Table1[[#This Row],[NEC Eligibility]]=TRUE,Table1[[#This Row],[Gross Pay]]*'Tax Tables'!$B$14,"") -> 0 | K11: =IFERROR(Table1[[#This Row],[NEC]]/2,"0") -> 0 | L11: =IF(Table1[[#This Row],[Gross Pay]]>'Tax Tables'!$D$13,'Tax Tables'!$D$13*'Tax Tables'!$B$13,Table1[[#This Row],[Gross Pay]]*'Tax Tables'!$B$13) -> 0 | M11: =Table1[[#This Row],[NSSA]]/2 -> 0 | N11: =Table1[[#This Row],[Gross Pay]]-Table1[[#This Row],[Trade Union]]-Table1[[#This Row],[NEC Employee]]-Table1[[#This Row],[NSSA Employee]] -> 0 | O11: =IF(Table1[[#This Row],[Taxable Income]]<='Tax Tables'!$B$3,'Tax Tables'!$C$3,IF(Table1[[#This Row],[Taxable Income]]<='Tax Tables'!$B$4,'Tax Tables'!$C$4,IF(Table1[[#This Row],[Taxable Income]]<='Tax Tables'!$B$5,'Tax Tables'!$C$5,IF(Table1[[#This Row],[Taxable Income]]<='Tax Tables'!$B$6,'Tax Tables'!$C$6,IF(Table1[[#This Row],[Taxable Income]]<='Tax Tables'!$B$7,'Tax Tables'!$C$7,IF(Table1[[#This Row],[Taxable Income]]>='Tax Tables'!$A$8,'Tax Tables'!$C$8)))))) -> 0 | P11: =IF(Table1[[#This Row],[Tax Rate]]='Tax Tables'!$C$3,'Tax Tables'!$D$3,IF(Table1[[#This Row],[Tax Rate]]='Tax Tables'!$C$4,'Tax Tables'!$D$4,IF(Table1[[#This Row],[Tax Rate]]='Tax Tables'!$C$5,'Tax Tables'!$D$5,IF(Table1[[#This Row],[Tax Rate]]='Tax Tables'!$C$6,'Tax Tables'!$D$6,IF(Table1[[#This Row],[Tax Rate]]='Tax Tables'!$C$7,'Tax Tables'!$D$7,IF(Table1[[#This Row],[Tax Rate]]='Tax Tables'!$C$8,'Tax Tables'!$D$8)))))) -> 0 | Q11: =Table1[[#This Row],[Taxable Income]]*Table1[[#This Row],[Tax Rate]]-(Table1[[#This Row],[Deduction]]) -> 0 | R11: =Table1[[#This Row],[PAYE]]*'Tax Tables'!$B$11 -> 0 | S11: =Table1[[#This Row],[PAYE]]+Table1[[#This Row],[AIDS Levy]] -> 0 | T11: =Table1[[#This Row],[PAYE]]+Table1[[#This Row],[AIDS Levy]]+Table1[[#This Row],[NSSA Employee]]+Table1[[#This Row],[NEC Employee]] -> 0 | U11: =Table1[[#This Row],[Taxable Income]]-Table1[[#This Row],[PAYE ZIMRA]]+Table1[[#This Row],[Yearly Bonus]]+Table1[[#This Row],[Bonus]] -> 0 | V11: 0 | W11: =Table1[[#This Row],[Net Pay]]-Table1[[#This Row],[Advance Deductions]] -> 0
C12: TRUE | H12: =Table1[[#This Row],[Gross Pay]]*'Tax Tables'!$B$16 -> 0 | I12: =Table1[[#This Row],[Gross Pay]]*'Tax Tables'!$B$15 -> 0 | J12: =IF(Table1[[#This Row],[NEC Eligibility]]=TRUE,Table1[[#This Row],[Gross Pay]]*'Tax Tables'!$B$14,"") -> 0 | K12: =IFERROR(Table1[[#This Row],[NEC]]/2,"0") -> 0 | L12: =IF(Table1[[#This Row],[Gross Pay]]>'Tax Tables'!$D$13,'Tax Tables'!$D$13*'Tax Tables'!$B$13,Table1[[#This Row],[Gross Pay]]*'Tax Tables'!$B$13) -> 0 | M12: =Table1[[#This Row],[NSSA]]/2 -> 0 | N12: =Table1[[#This Row],[Gross Pay]]-Table1[[#This Row],[Trade Union]]-Table1[[#This Row],[NEC Employee]]-Table1[[#This Row],[NSSA Employee]] -> 0 | O12: =IF(Table1[[#This Row],[Taxable Income]]<='Tax Tables'!$B$3,'Tax Tables'!$C$3,IF(Table1[[#This Row],[Taxable Income]]<='Tax Tables'!$B$4,'Tax Tables'!$C$4,IF(Table1[[#This Row],[Taxable Income]]<='Tax Tables'!$B$5,'Tax Tables'!$C$5,IF(Table1[[#This Row],[Taxable Income]]<='Tax Tables'!$B$6,'Tax Tables'!$C$6,IF(Table1[[#This Row],[Taxable Income]]<='Tax Tables'!$B$7,'Tax Tables'!$C$7,IF(Table1[[#This Row],[Taxable Income]]>='Tax Tables'!$A$8,'Tax Tables'!$C$8)))))) -> 0 | P12: =IF(Table1[[#This Row],[Tax Rate]]='Tax Tables'!$C$3,'Tax Tables'!$D$3,IF(Table1[[#This Row],[Tax Rate]]='Tax Tables'!$C$4,'Tax Tables'!$D$4,IF(Table1[[#This Row],[Tax Rate]]='Tax Tables'!$C$5,'Tax Tables'!$D$5,IF(Table1[[#This Row],[Tax Rate]]='Tax Tables'!$C$6,'Tax Tables'!$D$6,IF(Table1[[#This Row],[Tax Rate]]='Tax Tables'!$C$7,'Tax Tables'!$D$7,IF(Table1[[#This Row],[Tax Rate]]='Tax Tables'!$C$8,'Tax Tables'!$D$8)))))) -> 0 | Q12: =Table1[[#This Row],[Taxable Income]]*Table1[[#This Row],[Tax Rate]]-(Table1[[#This Row],[Deduction]]) -> 0 | R12: =Table1[[#This Row],[PAYE]]*'Tax Tables'!$B$11 -> 0 | S12: =Table1[[#This Row],[PAYE]]+Table1[[#This Row],[AIDS Levy]] -> 0 | T12: =Table1[[#This Row],[PAYE]]+Table1[[#This Row],[AIDS Levy]]+Table1[[#This Row],[NSSA Employee]]+Table1[[#This Row],[NEC Employee]] -> 0 | U12: =Table1[[#This Row],[Taxable Income]]-Table1[[#This Row],[PAYE ZIMRA]]+Table1[[#This Row],[Yearly Bonus]]+Table1[[#This Row],[Bonus]] -> 0 | V12: 0 | W12: =Table1[[#This Row],[Net Pay]]-Table1[[#This Row],[Advance Deductions]] -> 0
C13: TRUE | H13: =Table1[[#This Row],[Gross Pay]]*'Tax Tables'!$B$16 -> 0 | I13: =Table1[[#This Row],[Gross Pay]]*'Tax Tables'!$B$15 -> 0 | J13: =IF(Table1[[#This Row],[NEC Eligibility]]=TRUE,Table1[[#This Row],[Gross Pay]]*'Tax Tables'!$B$14,"") -> 0 | K13: =IFERROR(Table1[[#This Row],[NEC]]/2,"0") -> 0 | L13: =IF(Table1[[#This Row],[Gross Pay]]>'Tax Tables'!$D$13,'Tax Tables'!$D$13*'Tax Tables'!$B$13,Table1[[#This Row],[Gross Pay]]*'Tax Tables'!$B$13) -> 0 | M13: =Table1[[#This Row],[NSSA]]/2 -> 0 | N13: =Table1[[#This Row],[Gross Pay]]-Table1[[#This Row],[Trade Union]]-Table1[[#This Row],[NEC Employee]]-Table1[[#This Row],[NSSA Employee]] -> 0 | O13: =IF(Table1[[#This Row],[Taxable Income]]<='Tax Tables'!$B$3,'Tax Tables'!$C$3,IF(Table1[[#This Row],[Taxable Income]]<='Tax Tables'!$B$4,'Tax Tables'!$C$4,IF(Table1[[#This Row],[Taxable Income]]<='Tax Tables'!$B$5,'Tax Tables'!$C$5,IF(Table1[[#This Row],[Taxable Income]]<='Tax Tables'!$B$6,'Tax Tables'!$C$6,IF(Table1[[#This Row],[Taxable Income]]<='Tax Tables'!$B$7,'Tax Tables'!$C$7,IF(Table1[[#This Row],[Taxable Income]]>='Tax Tables'!$A$8,'Tax Tables'!$C$8)))))) -> 0 | P13: =IF(Table1[[#This Row],[Tax Rate]]='Tax Tables'!$C$3,'Tax Tables'!$D$3,IF(Table1[[#This Row],[Tax Rate]]='Tax Tables'!$C$4,'Tax Tables'!$D$4,IF(Table1[[#This Row],[Tax Rate]]='Tax Tables'!$C$5,'Tax Tables'!$D$5,IF(Table1[[#This Row],[Tax Rate]]='Tax Tables'!$C$6,'Tax Tables'!$D$6,IF(Table1[[#This Row],[Tax Rate]]='Tax Tables'!$C$7,'Tax Tables'!$D$7,IF(Table1[[#This Row],[Tax Rate]]='Tax Tables'!$C$8,'Tax Tables'!$D$8)))))) -> 0 | Q13: =Table1[[#This Row],[Taxable Income]]*Table1[[#This Row],[Tax Rate]]-(Table1[[#This Row],[Deduction]]) -> 0 | R13: =Table1[[#This Row],[PAYE]]*'Tax Tables'!$B$11 -> 0 | S13: =Table1[[#This Row],[PAYE]]+Table1[[#This Row],[AIDS Levy]] -> 0 | T13: =Table1[[#This Row],[PAYE]]+Table1[[#This Row],[AIDS Levy]]+Table1[[#This Row],[NSSA Employee]]+Table1[[#This Row],[NEC Employee]] -> 0 | U13: =Table1[[#This Row],[Taxable Income]]-Table1[[#This Row],[PAYE ZIMRA]]+Table1[[#This Row],[Yearly Bonus]]+Table1[[#This Row],[Bonus]] -> 0 | V13: 0 | W13: =Table1[[#This Row],[Net Pay]]-Table1[[#This Row],[Advance Deductions]] -> 0
C14: TRUE | H14: =Table1[[#This Row],[Gross Pay]]*'Tax Tables'!$B$16 -> 0 | I14: =Table1[[#This Row],[Gross Pay]]*'Tax Tables'!$B$15 -> 0 | J14: =IF(Table1[[#This Row],[NEC Eligibility]]=TRUE,Table1[[#This Row],[Gross Pay]]*'Tax Tables'!$B$14,"") -> 0 | K14: =IFERROR(Table1[[#This Row],[NEC]]/2,"0") -> 0 | L14: =IF(Table1[[#This Row],[Gross Pay]]>'Tax Tables'!$D$13,'Tax Tables'!$D$13*'Tax Tables'!$B$13,Table1[[#This Row],[Gross Pay]]*'Tax Tables'!$B$13) -> 0 | M14: =Table1[[#This Row],[NSSA]]/2 -> 0 | N14: =Table1[[#This Row],[Gross Pay]]-Table1[[#This Row],[Trade Union]]-Table1[[#This Row],[NEC Employee]]-Table1[[#This Row],[NSSA Employee]] -> 0 | O14: =IF(Table1[[#This Row],[Taxable Income]]<='Tax Tables'!$B$3,'Tax Tables'!$C$3,IF(Table1[[#This Row],[Taxable Income]]<='Tax Tables'!$B$4,'Tax Tables'!$C$4,IF(Table1[[#This Row],[Taxable Income]]<='Tax Tables'!$B$5,'Tax Tables'!$C$5,IF(Table1[[#This Row],[Taxable Income]]<='Tax Tables'!$B$6,'Tax Tables'!$C$6,IF(Table1[[#This Row],[Taxable Income]]<='Tax Tables'!$B$7,'Tax Tables'!$C$7,IF(Table1[[#This Row],[Taxable Income]]>='Tax Tables'!$A$8,'Tax Tables'!$C$8)))))) -> 0 | P14: =IF(Table1[[#This Row],[Tax Rate]]='Tax Tables'!$C$3,'Tax Tables'!$D$3,IF(Table1[[#This Row],[Tax Rate]]='Tax Tables'!$C$4,'Tax Tables'!$D$4,IF(Table1[[#This Row],[Tax Rate]]='Tax Tables'!$C$5,'Tax Tables'!$D$5,IF(Table1[[#This Row],[Tax Rate]]='Tax Tables'!$C$6,'Tax Tables'!$D$6,IF(Table1[[#This Row],[Tax Rate]]='Tax Tables'!$C$7,'Tax Tables'!$D$7,IF(Table1[[#This Row],[Tax Rate]]='Tax Tables'!$C$8,'Tax Tables'!$D$8)))))) -> 0 | Q14: =Table1[[#This Row],[Taxable Income]]*Table1[[#This Row],[Tax Rate]]-(Table1[[#This Row],[Deduction]]) -> 0 | R14: =Table1[[#This Row],[PAYE]]*'Tax Tables'!$B$11 -> 0 | S14: =Table1[[#This Row],[PAYE]]+Table1[[#This Row],[AIDS Levy]] -> 0 | T14: =Table1[[#This Row],[PAYE]]+Table1[[#This Row],[AIDS Levy]]+Table1[[#This Row],[NSSA Employee]]+Table1[[#This Row],[NEC Employee]] -> 0 | U14: =Table1[[#This Row],[Taxable Income]]-Table1[[#This Row],[PAYE ZIMRA]]+Table1[[#This Row],[Yearly Bonus]]+Table1[[#This Row],[Bonus]] -> 0 | V14: 0 | W14: =Table1[[#This Row],[Net Pay]]-Table1[[#This Row],[Advance Deductions]] -> 0
C15: FALSE | H15: =Table1[[#This Row],[Gross Pay]]*'Tax Tables'!$B$16 -> 0 | I15: =Table1[[#This Row],[Gross Pay]]*'Tax Tables'!$B$15 -> 0 | J15: =IF(Table1[[#This Row],[NEC Eligibility]]=TRUE,Table1[[#This Row],[Gross Pay]]*'Tax Tables'!$B$14,"") | K15: =IFERROR(Table1[[#This Row],[NEC]]/2,"0") -> 0 | L15: =IF(Table1[[#This Row],[Gross Pay]]>'Tax Tables'!$D$13,'Tax Tables'!$D$13*'Tax Tables'!$B$13,Table1[[#This Row],[Gross Pay]]*'Tax Tables'!$B$13) -> 0 | M15: =Table1[[#This Row],[NSSA]]/2 -> 0 | N15: =Table1[[#This Row],[Gross Pay]]-Table1[[#This Row],[Trade Union]]-Table1[[#This Row],[NEC Employee]]-Table1[[#This Row],[NSSA Employee]] -> 0 | O15: =IF(Table1[[#This Row],[Taxable Income]]<='Tax Tables'!$B$3,'Tax Tables'!$C$3,IF(Table1[[#This Row],[Taxable Income]]<='Tax Tables'!$B$4,'Tax Tables'!$C$4,IF(Table1[[#This Row],[Taxable Income]]<='Tax Tables'!$B$5,'Tax Tables'!$C$5,IF(Table1[[#This Row],[Taxable Income]]<='Tax Tables'!$B$6,'Tax Tables'!$C$6,IF(Table1[[#This Row],[Taxable Income]]<='Tax Tables'!$B$7,'Tax Tables'!$C$7,IF(Table1[[#This Row],[Taxable Income]]>='Tax Tables'!$A$8,'Tax Tables'!$C$8)))))) -> 0 | P15: =IF(Table1[[#This Row],[Tax Rate]]='Tax Tables'!$C$3,'Tax Tables'!$D$3,IF(Table1[[#This Row],[Tax Rate]]='Tax Tables'!$C$4,'Tax Tables'!$D$4,IF(Table1[[#This Row],[Tax Rate]]='Tax Tables'!$C$5,'Tax Tables'!$D$5,IF(Table1[[#This Row],[Tax Rate]]='Tax Tables'!$C$6,'Tax Tables'!$D$6,IF(Table1[[#This Row],[Tax Rate]]='Tax Tables'!$C$7,'Tax Tables'!$D$7,IF(Table1[[#This Row],[Tax Rate]]='Tax Tables'!$C$8,'Tax Tables'!$D$8)))))) -> 0 | Q15: =Table1[[#This Row],[Taxable Income]]*Table1[[#This Row],[Tax Rate]]-(Table1[[#This Row],[Deduction]]) -> 0 | R15: =Table1[[#This Row],[PAYE]]*'Tax Tables'!$B$11 -> 0 | S15: =Table1[[#This Row],[PAYE]]+Table1[[#This Row],[AIDS Levy]] -> 0 | T15: =Table1[[#This Row],[PAYE]]+Table1[[#This Row],[AIDS Levy]]+Table1[[#This Row],[NSSA Employee]]+Table1[[#This Row],[NEC Employee]] -> 0 | U15: =Table1[[#This Row],[Taxable Income]]-Table1[[#This Row],[PAYE ZIMRA]]+Table1[[#This Row],[Yearly Bonus]]+Table1[[#This Row],[Bonus]] -> 0 | V15: 0 | W15: =Table1[[#This Row],[Net Pay]]-Table1[[#This Row],[Advance Deductions]] -> 0
... C29: TRUE | H29: =Table1[[#This Row],[Gross Pay]]*'Tax Tables'!$B$16 -> 0 | I29: =Table1[[#This Row],[Gross Pay]]*'Tax Tables'!$B$15 -> 0 | J29: =IF(Table1[[#This Row],[NEC Eligibility]]=TRUE,Table1[[#This Row],[Gross Pay]]*'Tax Tables'!$B$14,"") -> 0 | K29: =IFERROR(Table1[[#This Row],[NEC]]/2,"0") -> 0 | L29: =IF(Table1[[#This Row],[Gross Pay]]>'Tax Tables'!$D$13,'Tax Tables'!$D$13*'Tax Tables'!$B$13,Table1[[#This Row],[Gross Pay]]*'Tax Tables'!$B$13) -> 0 | M29: =Table1[[#This Row],[NSSA]]/2 -> 0 | N29: =Table1[[#This Row],[Gross Pay]]-Table1[[#This Row],[Trade Union]]-Table1[[#This Row],[NEC Employee]]-Table1[[#This Row],[NSSA Employee]] -> 0 | O29: =IF(Table1[[#This Row],[Taxable Income]]<='Tax Tables'!$B$3,'Tax Tables'!$C$3,IF(Table1[[#This Row],[Taxable Income]]<='Tax Tables'!$B$4,'Tax Tables'!$C$4,IF(Table1[[#This Row],[Taxable Income]]<='Tax Tables'!$B$5,'Tax Tables'!$C$5,IF(Table1[[#This Row],[Taxable Income]]<='Tax Tables'!$B$6,'Tax Tables'!$C$6,IF(Table1[[#This Row],[Taxable Income]]<='Tax Tables'!$B$7,'Tax Tables'!$C$7,IF(Table1[[#This Row],[Taxable Income]]>='Tax Tables'!$A$8,'Tax Tables'!$C$8)))))) -> 0 | P29: =IF(Table1[[#This Row],[Tax Rate]]='Tax Tables'!$C$3,'Tax Tables'!$D$3,IF(Table1[[#This Row],[Tax Rate]]='Tax Tables'!$C$4,'Tax Tables'!$D$4,IF(Table1[[#This Row],[Tax Rate]]='Tax Tables'!$C$5,'Tax Tables'!$D$5,IF(Table1[[#This Row],[Tax Rate]]='Tax Tables'!$C$6,'Tax Tables'!$D$6,IF(Table1[[#This Row],[Tax Rate]]='Tax Tables'!$C$7,'Tax Tables'!$D$7,IF(Table1[[#This Row],[Tax Rate]]='Tax Tables'!$C$8,'Tax Tables'!$D$8)))))) -> 0 | Q29: =Table1[[#This Row],[Taxable Income]]*Table1[[#This Row],[Tax Rate]]-(Table1[[#This Row],[Deduction]]) -> 0 | R29: =Table1[[#This Row],[PAYE]]*'Tax Tables'!$B$11 -> 0 | S29: =Table1[[#This Row],[PAYE]]+Table1[[#This Row],[AIDS Levy]] -> 0 | T29: =Table1[[#This Row],[PAYE]]+Table1[[#This Row],[AIDS Levy]]+Table1[[#This Row],[NSSA Employee]]+Table1[[#This Row],[NEC Employee]] -> 0 | U29: =Table1[[#This Row],[Taxable Income]]-Table1[[#This Row],[PAYE ZIMRA]]+Table1[[#This Row],[Yearly Bonus]]+Table1[[#This Row],[Bonus]] -> 0 | V29: 0 | W29: =Table1[[#This Row],[Net Pay]]-Table1[[#This Row],[Advance Deductions]] -> 0
E30: =SUBTOTAL(109,Table1[Gross Pay]) -> 1200 | F30: =SUBTOTAL(109,Table1[Bonus]) -> 0 | G30: =SUBTOTAL(109,Table1[Yearly Bonus]) -> 0 | H30: =SUBTOTAL(109,Table1[WCIF]) -> 15 | I30: =SUBTOTAL(109,Table1[Trade Union]) -> 0 | J30: =SUBTOTAL(109,Table1[NEC]) -> 0 | K30: =SUBTOTAL(109,Table1[NEC Employee]) -> 0 | L30: =SUBTOTAL(109,Table1[NSSA]) -> 63 | M30: =SUBTOTAL(109,Table1[NSSA Employee]) -> 31.5 | N30: =SUBTOTAL(109,Table1[Taxable Income]) -> 1168.5 | Q30: =SUBTOTAL(109,Table1[PAYE]) -> 265.55 | R30: =SUBTOTAL(109,Table1[AIDS Levy]) -> 7.9665 | S30: =SUBTOTAL(109,Table1[PAYE ZIMRA]) -> 273.5165 | T30: =SUBTOTAL(109,Table1[Total Deductions]) -> 305.0165 | U30: =SUBTOTAL(109,Table1[Net Pay]) -> 894.9835 | W30: =SUBTOTAL(109,Table1[Net Pay after Deductions]) -> 894.9835

Sheet Tax Tables
A1: USD Tax Tables 2025
A3: 0 | B3: 100 | C3: 0 | D3: 0
A4: 100.01 | B4: 300 | C4: 0.2 | D4: 20
A5: 300.01 | B5: 1000 | C5: 0.25 | D5: 35
A6: 1000.01 | B6: 2000 | C6: 0.3 | D6: 85
A7: 2000.01 | B7: 3000 | C7: 0.35 | D7: 185
A8: 3000.01 | C8: 0.4 | D8: 335
A11: AIDS Levy | B11: 0.03
A13: NSSA | B13: 0.09 | D13: 700
A14: NEC | B14: 0.02
A15: Trade Union
A16: WCIF | B16: 0.0125

Sheet Payroll Journals
D2: Debit | E2: Credit
C3: Gross Pay | D3: ='Payroll Calculations '!E30 -> 1200
C4: Bonus | D4: =Table1[[#Totals],[Bonus]]+Table1[[#Totals],[Yearly Bonus]] -> 0
C5: Trade Union | E5: =Table1[[#Totals],[Trade Union]] -> 0
C6: NEC Employee | E6: =Table1[[#Totals],[NEC Employee]] -> 0
C7: NSSA Employee | E7: =Table1[[#Totals],[NSSA Employee]] -> 31.5
C8: PAYE | E8: =Table1[[#Totals],[PAYE]] -> 265.55
C9: AIDS Levy | E9: =Table1[[#Totals],[AIDS Levy]] -> 7.9665
C10: Net Pay | E10: =Table1[[#Totals],[Net Pay]] -> 894.9835
D11: =SUM(D3:D10) -> 1200 | E11: =SUM(E5:E10) -> 1200
C14: Statutory Payments
C15: PAYE | D15: =Table1[[#Totals],[PAYE]] -> 265.55
C16: AIDS Levy | D16: =Table1[[#Totals],[AIDS Levy]] -> 7.9665
C17: NEC | D17: =Table1[[#Totals],[NEC]] -> 0
C18: NSSA | D18: =Table1[[#Totals],[NSSA]] -> 63
C19: WCIF | D19: =Table1[[#Totals],[WCIF]] -> 15
D20: =SUM(D15:D19) -> 351.5165
